README.md
SillyProcessing.py
setup.py
SillyProcessing.egg-info/PKG-INFO
SillyProcessing.egg-info/SOURCES.txt
SillyProcessing.egg-info/dependency_links.txt
SillyProcessing.egg-info/requires.txt
SillyProcessing.egg-info/top_level.txt