Metadata-Version: 2.1
Name: SillyProcessing
Version: 0.1.0
Summary: A wheel that can help you to work of program.
Home-page: https://github.com/JudyInRedHat/SillyProcessing
Author: 翟嘉琳
Author-email: 1905655735@qq.com
License: MIT
Platform: UNKNOWN
Classifier: License :: OSI Approved :: MIT License
Classifier: Programming Language :: Python
Classifier: Programming Language :: Python :: 3
Classifier: Programming Language :: Python :: 3.6
Classifier: Programming Language :: Python :: Implementation :: CPython
Classifier: Programming Language :: Python :: Implementation :: PyPy
Requires-Python: >=3.9.0
